leo3d/__init__.py
leo3d/window.py
leo3d-0.1.0.dist-info/METADATA
leo3d-0.1.0.dist-info/WHEEL
leo3d-0.1.0.dist-info/top_level.txt
leo3d-0.1.0.dist-info/RECORD
