Metadata-Version: 2.4
Name: leo3d
Version: 0.1.0
Summary: Python + Native OpenGL 3D Engine
Requires-Python: >=3.10
